Metadata-Version: 2.1
Name: iltrcli
Version: 1.0.0
License-File: LICENSE.txt
Requires-Dist: click (==8.0.*)
Requires-Dist: pyyaml (==6.0.*)
Requires-Dist: junitparser (==3.1.*)
Requires-Dist: pyserde (==0.12.*)
Requires-Dist: requests (==2.31.*)
Requires-Dist: tqdm (==4.65.*)
Requires-Dist: humanfriendly (==10.0.*)
Requires-Dist: openapi-spec-validator (==0.5.*)
Requires-Dist: prance
